ratchada_utils/__init__.py
ratchada_utils/evaluator/__init__.py
ratchada_utils/evaluator/evaluate_utils.py
ratchada_utils/processor/__init__.py
ratchada_utils/processor/basic.py
ratchada_utils/processor/english.json
ratchada_utils/processor/english.py
ratchada_utils/processor/postfix.py
ratchada_utils/processor/process.py
ratchada_utils-2.2.6.dist-info/LICENSE
ratchada_utils-2.2.6.dist-info/METADATA
ratchada_utils-2.2.6.dist-info/WHEEL
ratchada_utils-2.2.6.dist-info/top_level.txt
ratchada_utils-2.2.6.dist-info/RECORD
