Metadata-Version: 2.1
Name: ratchada_utils
Version: 2.2.6
Summary: Ratchada Utils are Python package use with Ratchada Whisper model utilities.
Home-page: https://github.com/thinkingmachines/ratchada-utils/
Author: tm-zoon
Author-email: zoon_p@thinkingmachin.es
License: MIT
Project-URL: Documentation, https://huggingface.co/ThinkingMachinesDataScience/Ratchada-Fang-Thon-Whisper
Project-URL: Source Code, https://github.com/thinkingmachines/ratchada-utils
Project-URL: Issue Tracker, https://github.com/thinkingmachines/ratchada-utils/issues
Keywords: model,Ratchada-Whisper,tokenizing,language,natural language,text analytics
Classifier: Intended Audience :: Developers
Classifier: Intended Audience :: Education
Classifier: Intended Audience :: Information Technology
Classifier: Intended Audience :: Science/Research
Classifier: License :: OSI Approved :: MIT License
Classifier: Operating System :: OS Independent
Classifier: Programming Language :: Python :: 3.10
Classifier: Programming Language :: Python :: 3.11
Classifier: Topic :: Scientific/Engineering
Classifier: Topic :: Scientific/Engineering :: Artificial Intelligence
Classifier: Topic :: Scientific/Engineering :: Information Analysis
Classifier: Topic :: Text Processing
Classifier: Topic :: Text Processing :: Filters
Classifier: Topic :: Text Processing :: General
Classifier: Topic :: Text Processing :: Indexing
Classifier: Topic :: Text Processing :: Linguistic
Requires-Python: >=3.10, <3.12
License-File: LICENSE
Requires-Dist: deepcut ==0.7.0.0 ; python_version >= "3.10" and python_version < "3.12"
Requires-Dist: ipython ==8.26.0 ; python_version >= "3.10" and python_version < "3.12"
Requires-Dist: jiwer ==3.0.3 ; python_version >= "3.10" and python_version < "3.12"
Requires-Dist: langdetect ==1.0.9 ; python_version >= "3.10" and python_version < "3.12"
Requires-Dist: more-itertools ==10.1.0 ; python_version >= "3.10" and python_version < "3.12"
Requires-Dist: pandas ==2.1.3 ; python_version >= "3.10" and python_version < "3.12"
Requires-Dist: pre-commit ==3.7.1 ; python_version >= "3.10" and python_version < "3.12"
Requires-Dist: regex ==2023.10.3 ; python_version >= "3.10" and python_version < "3.12"
